pystellardb/__init__.py
pystellardb/_version.py
pystellardb/graph_types.py
pystellardb/sasl_compat.py
pystellardb/stellar_hive.py
pystellardb/stellar_rdd.py
pystellardb/v2/__init__.py
pystellardb/v2/connection.py
pystellardb/v2/database.py
PyStellarDB-1.0.1.dist-info/LICENSE
PyStellarDB-1.0.1.dist-info/METADATA
PyStellarDB-1.0.1.dist-info/WHEEL
PyStellarDB-1.0.1.dist-info/top_level.txt
PyStellarDB-1.0.1.dist-info/RECORD
