Metadata-Version: 2.2
Name: PyStellarDB
Version: 1.0.1
Summary: Python interface to StellarDB
Home-page: https://github.com/WarpCloud/PyStellarDB
Author: Zhiping Wang
Author-email: zhiping.wang@transwarp.io
License: Apache License, Version 2.0
Classifier: Intended Audience :: Developers
Classifier: License :: OSI Approved :: Apache Software License
Classifier: Operating System :: OS Independent
Classifier: Topic :: Database :: Front-Ends
Requires-Python: >=3.6
License-File: LICENSE
Requires-Dist: future
Requires-Dist: python-dateutil
Requires-Dist: pyhive[hive_pure_sasl]
Requires-Dist: thrift>=0.10.0
Provides-Extra: pyspark
Requires-Dist: pyspark>=2.4.0; extra == "pyspark"
Provides-Extra: kerberos
Requires-Dist: kerberos>=1.3.0; extra == "kerberos"
Dynamic: author
Dynamic: author-email
Dynamic: classifier
Dynamic: description
Dynamic: home-page
Dynamic: license
Dynamic: provides-extra
Dynamic: requires-dist
Dynamic: requires-python
Dynamic: summary
